setup.py
porv_distributions/Binomialdistribution.py
porv_distributions/Gaussiandistribution.py
porv_distributions/Generaldistribution.py
porv_distributions/__init__.py
porv_distributions.egg-info/PKG-INFO
porv_distributions.egg-info/SOURCES.txt
porv_distributions.egg-info/dependency_links.txt
porv_distributions.egg-info/not-zip-safe
porv_distributions.egg-info/top_level.txt