Metadata-Version: 1.0
Name: porv-distributions
Version: 0.1
Summary: Gaussian and Binomial distributions
Home-page: UNKNOWN
Author: Praveen Orvakanti
Author-email: praveen.orvakanti@gmail.com
License: UNKNOWN
Platform: UNKNOWN
